ifra_sdk/__init__.py
ifra_sdk/client.py
ifra_sdk/resource_monitoring.py
ifra_sdk-1.0.6.dist-info/METADATA
ifra_sdk-1.0.6.dist-info/WHEEL
ifra_sdk-1.0.6.dist-info/top_level.txt
ifra_sdk-1.0.6.dist-info/RECORD
